dbopenapi/OpenApi.py
dbopenapi/__init__.py
dbopenapi/code_realtime_account.py
dbopenapi/tr_code_to_path.py
dbopenapi-0.0.8.dist-info/METADATA
dbopenapi-0.0.8.dist-info/WHEEL
dbopenapi-0.0.8.dist-info/licenses/LICENSE
dbopenapi-0.0.8.dist-info/RECORD
