Metadata-Version: 2.3
Name: dbopenapi
Version: 0.0.8
Summary: package for db openapi
Project-URL: Homepage, https://github.com/teranum/python-packages/tree/master/dbopenapi
Project-URL: Issues, https://github.com/teranum/python-packages/issues
Author-email: teranum <teranum@gmail.com>
License-File: LICENSE
Classifier: License :: OSI Approved :: MIT License
Classifier: Operating System :: OS Independent
Classifier: Programming Language :: Python :: 3
Requires-Python: >=3.8
Requires-Dist: aiohttp
